README.md
orbit_database/README.md
orbit_database/__init__.py
orbit_database/audit.py
orbit_database/bitmap.py
orbit_database/catalog.py
orbit_database/compression.py
orbit_database/cursor.py
orbit_database/database.py
orbit_database/decorators.py
orbit_database/doc.py
orbit_database/exceptions.py
orbit_database/filterresult.py
orbit_database/index.py
orbit_database/iwx.py
orbit_database/manager.py
orbit_database/matchresult.py
orbit_database/metadata.py
orbit_database/objectid.py
orbit_database/serialiser.py
orbit_database/table.py
orbit_database-1.0.20.dist-info/LICENSE
orbit_database-1.0.20.dist-info/METADATA
orbit_database-1.0.20.dist-info/WHEEL
orbit_database-1.0.20.dist-info/RECORD
