Metadata-Version: 2.1
Name: orbit_database
Version: 1.0.20
Summary: Database library for Python based on LMDB storage engine
Home-page: https://gitlab.com/madpenguin/orbit-database
Keywords: database,nosql,lmdb
Author: Gareth Bult
Author-email: gareth@madpenguin.uk
Requires-Python: >=3.8,<4.0
Classifier: Development Status :: 4 - Beta
Classifier: Intended Audience :: Developers
Classifier: License :: OSI Approved :: MIT License
Classifier: Operating System :: OS Independent
Classifier: Programming Language :: Python :: 3
Classifier: Programming Language :: Python :: 3.8
Classifier: Programming Language :: Python :: 3.9
Classifier: Programming Language :: Python :: 3.10
Classifier: Programming Language :: Python :: 3.11
Classifier: Topic :: Database :: Database Engines/Servers
Classifier: Topic :: Software Development :: Libraries :: Python Modules
Requires-Dist: lmdb (>=1.4.1,<2.0.0)
Requires-Dist: posix-ipc (>=1.1.1,<2.0.0)
Requires-Dist: typing-extensions (>=4.7.1,<5.0.0)
Project-URL: Documentation, https://gitlab.com/madpenguin/orbit-database
Project-URL: Repository, https://gitlab.com/madpenguin/orbit-database
